iris/__init__.py
iris/_combine.py
iris/_concatenate.py
iris/_constraints.py
iris/_data_manager.py
iris/_deprecation.py
iris/_lazy_data.py
iris/_merge.py
iris/_shapefiles.py
iris/_version.py
iris/aux_factory.py
iris/config.py
iris/coord_categorisation.py
iris/coord_systems.py
iris/coords.py
iris/cube.py
iris/exceptions.py
iris/iterate.py
iris/loading.py
iris/palette.py
iris/pandas.py
iris/plot.py
iris/quickplot.py
iris/std_names.py
iris/symbols.py
iris/time.py
iris/util.py
iris/warnings.py
iris/_representation/__init__.py
iris/_representation/cube_printout.py
iris/_representation/cube_summary.py
iris/analysis/__init__.py
iris/analysis/_area_weighted.py
iris/analysis/_grid_angles.py
iris/analysis/_interpolation.py
iris/analysis/_regrid.py
iris/analysis/_scipy_interpolate.py
iris/analysis/calculus.py
iris/analysis/cartography.py
iris/analysis/geometry.py
iris/analysis/maths.py
iris/analysis/stats.py
iris/analysis/trajectory.py
iris/common/__init__.py
iris/common/_split_attribute_dicts.py
iris/common/lenient.py
iris/common/metadata.py
iris/common/mixin.py
iris/common/resolve.py
iris/etc/site.cfg.template
iris/etc/palette/diverging/BrBG_11.txt
iris/etc/palette/diverging/PRGn_11.txt
iris/etc/palette/diverging/PiYG_11.txt
iris/etc/palette/diverging/PuOr_11.txt
iris/etc/palette/diverging/RdBu_11.txt
iris/etc/palette/diverging/RdGy_11.txt
iris/etc/palette/diverging/RdYlBu_11.txt
iris/etc/palette/diverging/RdYlGn_11.txt
iris/etc/palette/diverging/Spectral_11.txt
iris/etc/palette/qualitative/Accent_08.txt
iris/etc/palette/qualitative/Dark2_08.txt
iris/etc/palette/qualitative/Paired_12.txt
iris/etc/palette/qualitative/Pastel1_09.txt
iris/etc/palette/qualitative/Pastel2_08.txt
iris/etc/palette/qualitative/Set1_09.txt
iris/etc/palette/qualitative/Set2_08.txt
iris/etc/palette/qualitative/Set3_12.txt
iris/etc/palette/sequential/Blues_09.txt
iris/etc/palette/sequential/BuGn_09.txt
iris/etc/palette/sequential/BuPu_09.txt
iris/etc/palette/sequential/GnBu_09.txt
scitools_iris-3.14.0.dist-info/licenses/LICENSE
scitools_iris-3.14.0.dist-info/METADATA
scitools_iris-3.14.0.dist-info/WHEEL
scitools_iris-3.14.0.dist-info/top_level.txt
scitools_iris-3.14.0.dist-info/RECORD
