Metadata-Version: 2.4
Name: scitools-iris
Version: 3.14.0
Summary: A powerful, format-agnostic, community-driven Python package for analysing and visualising Earth science data
Author-email: Iris Contributors <scitools.pub@gmail.com>
License-Expression: BSD-3-Clause
Project-URL: Code, https://github.com/SciTools/iris
Project-URL: Discussions, https://github.com/SciTools/iris/discussions
Project-URL: Documentation, https://scitools-iris.readthedocs.io/en/stable/
Project-URL: Issues, https://github.com/SciTools/iris/issues
Keywords: cf-metadata,data-analysis,earth-science,grib,netcdf,meteorology,oceanography,space-weather,ugrid,visualisation
Classifier: Development Status :: 5 - Production/Stable
Classifier: Intended Audience :: Science/Research
Classifier: Operating System :: MacOS
Classifier: Operating System :: POSIX
Classifier: Operating System :: POSIX :: Linux
Classifier: Operating System :: Unix
Classifier: Programming Language :: Python
Classifier: Programming Language :: Python :: 3 :: Only
Classifier: Programming Language :: Python :: 3.11
Classifier: Programming Language :: Python :: 3.12
Classifier: Programming Language :: Python :: 3.13
Classifier: Programming Language :: Python :: Implementation :: CPython
Classifier: Topic :: Scientific/Engineering
Classifier: Topic :: Scientific/Engineering :: Atmospheric Science
Classifier: Topic :: Scientific/Engineering :: Visualization
Requires-Python: <3.14,>=3.11
License-File: LICENSE
Requires-Dist: cartopy>=0.21
Requires-Dist: cf-units>=3.1
Requires-Dist: cftime>=1.5.0
Requires-Dist: dask[array]<2025.10.0,>=2025.1.0
Requires-Dist: matplotlib>=3.5
Requires-Dist: netcdf4<1.7.3
Requires-Dist: numpy!=1.24.3,>=1.24
Requires-Dist: pyproj
Requires-Dist: scipy
Requires-Dist: shapely!=1.8.3
Requires-Dist: xxhash
Dynamic: license-file
